onegov.applications-2019.8.9-py3.6-nspkg.pth
onegov/applications/.gitignore
onegov/applications/__init__.py
onegov/applications/applications.json
onegov/applications/tests/conftest.py
onegov/applications/tests/test_applications.py
onegov.applications-2019.8.9.dist-info/METADATA
onegov.applications-2019.8.9.dist-info/WHEEL
onegov.applications-2019.8.9.dist-info/namespace_packages.txt
onegov.applications-2019.8.9.dist-info/top_level.txt
onegov.applications-2019.8.9.dist-info/RECORD
