Metadata-Version: 2.1
Name: onegov.applications
Version: 2019.8.9
Summary: Meta-package containing all OneGov Cloud applications.
Home-page: http://github.com/OneGov/onegov.applications
Author: Seantis GmbH
Author-email: info@seantis.ch
License: GPLv2
Platform: any
Classifier: Intended Audience :: Developers
Classifier: Programming Language :: Python :: 3 :: Only
Classifier: Programming Language :: Python :: 3.6
Classifier: Programming Language :: Python :: 3.7
Classifier: Topic :: Software Development :: Libraries :: Python Modules
Classifier: License :: OSI Approved :: GNU General Public License v2 (GPLv2)
Requires-Python: >=3.6
Requires-Dist: onegov.org
Requires-Dist: onegov.town
Requires-Dist: onegov.feriennet
Requires-Dist: onegov.onboarding
Requires-Dist: onegov.election-day
Requires-Dist: onegov.gazette
Requires-Dist: onegov.intranet
Requires-Dist: onegov.winterthur
Requires-Dist: onegov.swissvotes
Requires-Dist: onegov.agency
Requires-Dist: onegov.wtfs
Provides-Extra: test
Requires-Dist: onegov.org[test] ; extra == 'test'
Requires-Dist: onegov.town[test] ; extra == 'test'
Requires-Dist: onegov.feriennet[test] ; extra == 'test'
Requires-Dist: onegov.onboarding[test] ; extra == 'test'
Requires-Dist: onegov.election-day[test] ; extra == 'test'
Requires-Dist: onegov.gazette[test] ; extra == 'test'
Requires-Dist: onegov.intranet[test] ; extra == 'test'
Requires-Dist: onegov.winterthur[test] ; extra == 'test'
Requires-Dist: onegov.swissvotes[test] ; extra == 'test'
Requires-Dist: onegov.agency[test] ; extra == 'test'
Requires-Dist: onegov.wtfs[test] ; extra == 'test'
